py_edgar_api/__init__.py
py_edgar_api/client.py
py_edgar_api/company.py
py_edgar_api-0.1.4.dist-info/METADATA
py_edgar_api-0.1.4.dist-info/WHEEL
py_edgar_api-0.1.4.dist-info/RECORD
